here_search/demo/__init__.py
here_search/demo/api.py
here_search/demo/api_options.py
here_search/demo/base.py
here_search/demo/event.py
here_search/demo/http.py
here_search/demo/lite.py
here_search/demo/user.py
here_search/demo/util.py
here_search/demo/entity/__init__.py
here_search/demo/entity/constants.py
here_search/demo/entity/endpoint.py
here_search/demo/entity/intent.py
here_search/demo/entity/place.py
here_search/demo/entity/request.py
here_search/demo/entity/response.py
here_search/demo/entity/response_data.py
here_search/demo/notebooks/_install.py
here_search/demo/widgets/__init__.py
here_search/demo/widgets/app.py
here_search/demo/widgets/input.py
here_search/demo/widgets/output.py
here_search/demo/widgets/util.py
here_search_demo-0.17.6.dist-info/licenses/LICENSE
here_search_demo-0.17.6.dist-info/METADATA
here_search_demo-0.17.6.dist-info/WHEEL
here_search_demo-0.17.6.dist-info/top_level.txt
here_search_demo-0.17.6.dist-info/RECORD
