Metadata-Version: 2.4
Name: here-search-demo
Version: 0.17.6
Summary: HERE Geocoding and Search demo and widgets
Author-email: "HERE Global B.V. and its affiliate(s)" <590094+decitre@users.noreply.github.com>
License-Expression: MIT
Project-URL: homepage, https://here.com
Project-URL: repository, https://github.com/heremaps/here-search-demo
Classifier: Development Status :: 4 - Beta
Classifier: Environment :: WebAssembly :: Emscripten
Classifier: Intended Audience :: Developers
Classifier: Natural Language :: English
Classifier: Programming Language :: Python :: 3
Classifier: Programming Language :: Python :: 3.10
Classifier: Programming Language :: Python :: 3.11
Classifier: Programming Language :: Python :: 3.12
Classifier: Programming Language :: Python :: 3.13
Classifier: Programming Language :: Python :: 3 :: Only
Classifier: Programming Language :: Python :: Implementation :: CPython
Requires-Python: >=3.10
License-File: LICENSE
Requires-Dist: ipyleaflet==0.20.0
Requires-Dist: ipywidgets==8.1.8
Requires-Dist: jupyterlab>=4.5.1
Requires-Dist: jupyterlab_widgets
Requires-Dist: jupyterlab-filesystem-access
Requires-Dist: jupyterlite~=0.7.1
Requires-Dist: jupyterlite-core
Requires-Dist: jupyterlite-pyodide-kernel
Requires-Dist: jupyterlite-javascript-kernel
Requires-Dist: libarchive-c
Requires-Dist: orjson<4,>=3.11.3
Requires-Dist: xyzservices>=2025.11.0
Provides-Extra: lab
Requires-Dist: aiohttp; extra == "lab"
Requires-Dist: xyzservices; extra == "lab"
Provides-Extra: dev
Requires-Dist: bumpver; extra == "dev"
Requires-Dist: pytest; extra == "dev"
Requires-Dist: pytest-asyncio; extra == "dev"
Requires-Dist: pytest-cov; extra == "dev"
Requires-Dist: ruff; extra == "dev"
Requires-Dist: isort; extra == "dev"
Dynamic: license-file
